[
  {
    "title": "Cute Bunny",
    "link": "http://f.cl.ly/items/3g3J1G0w122M360w380O/3726490195_f7cc75d377_o.jpg",
    "description": "Really, really cute bunny",
    "album": "Bunnies"
  },
  {
    "title": "Bugs",
    "link": "http://vignette1.wikia.nocookie.net/characters/images/1/15/Bugs.jpg/revision/latest?cb=20110224072532",
    "description": "Bugs Bunny - a classic",
    "album": "Bunnies"
  },
  {
    "title": "Bean Walking on the Moon",
    "link": "http://www.armaghplanet.com/blog/wp-content/uploads/2011/09/Image-of-as12-46-6728.jpg",
    "description": "Alan Bean leaving the lunar module to walk on the Moon during the Apollo 12 mission",
    "album": "Space"
  },
  {
    "title": "F-89 Scorpion",
    "link": "http://www.fiddlersgreen.net/aircraft/Northrop-F89/IMAGES/Northrop-F89-Scorpion-Jet-Interceptor-Title.jpg",
    "description": "The plane my Dad flew during his Air Force service",
    "album": "Planes"
  },
  {
    "title": "A-12 Avenger II",
    "link": "http://1.bp.blogspot.com/-Bs_UdCFFEr4/VjBh1KcgdnI/AAAAAAABM9I/ana71mftu3s/s1600/a_12_avenger_ii_by_japphell-d3ci05u.png",
    "description": "I worked on this plane",
    "album": "Planes"
  },
  {
    "title": "SR-71 Blackbird",
    "link": "https://upload.wikimedia.org/wikipedia/commons/9/97/Lockheed_SR-71_Blackbird.jpg",
    "description": "World's fastest plane for many decades",
    "album": "Planes"
  },
  {
    "title": "David Zabriskie Time Trial",
    "link": "https://upload.wikimedia.org/wikipedia/commons/thumb/d/d8/Dave_Zabriskie_-_USA_Pro_Time_Trial.jpg/1280px-Dave_Zabriskie_-_USA_Pro_Time_Trial.jpg?1481125420015",
    "description": "David is a very fast cyclist and has been clocked at 34 mph in the time trial, the 'race of truth'",
    "album": "Cycling"
  },
  {
    "title": "Team Time Trial",
    "link": "http://tiz-cycling.racing/wp-content/uploads/2016/10/Team-Time-Trial-World-Championships-2016-FULL-RACE.jpg",
    "description": "Going seriously fast...",
    "album": "Cycling"
  },
  {
    "title": "Bad Stuff Going Down",
    "link": "https://tunedintocycling.files.wordpress.com/2015/07/team-garmin-sharp-poc-crash-team-time-trial-giro-d-italia-2014.jpg",
    "description": "Sometimes s--t goes bad fast...",
    "album": "Cycling"
  },
  {
    "title": "Chicago Skyline",
    "link": "http://www.greencurtainevents.com/newsite/wp-content/uploads/2014/11/chicago-skyline-2.jpg",
    "description": "Chicago at dusk",
    "album": "Cityscapes"
  },
  {
    "title": "Washington DC Skyline",
    "link": "http://inspirationseek.com/wp-content/uploads/2014/12/Washington-DC-Skyline-Wallpaper-HD.jpg",
    "description": "The Mall in the Nation's Capital",
    "album": "Cityscapes"
  },
  {
    "title": "F/A-18 Super Hornet",
    "link": "http://www.boeing.com/resources/boeingdotcom/defense/fa-18_super_hornet/images/hornet_hero_lrg_01_1280x720.jpg",
    "description": "F/A-18 Super Hornet preparing to launch from carrier",
    "album": "Planes"
  },
  {
    "title": "Monty Python Killer Rabbit",
    "link": "https://s-media-cache-ak0.pinimg.com/236x/50/59/1f/50591f6231210fa7892733f7f0f15c18.jpg",
    "description": "Run away! Run away!",
    "album": "Bunnies"
  },
  {
    "title": "Space Shuttle",
    "link": "http://www.space-images.com/wallpapers/space-shuttle/05/shuttle_05_2560x1600.jpg",
    "description": "Open the pod bay doors, HAL...",
    "album": "Space"
  },
  {
    "title": "Portland Skyline",
    "link": "http://portland.ediblefeast.com/sites/default/files/images/article/portland-skyline-mt-hood_1.jpg",
    "description": "Portland, OR with Mt. Hood in the background",
    "album": "Cityscapes"
  }
]